dhl_ecom_de_lib/__init__.py
dhl_ecom_de_lib/business_interface.py
dhl_ecom_de_lib/customer_interface.py
carrier.dhl_ecom_de-2021.10rc0.dist-info/WHEEL
carrier.dhl_ecom_de-2021.10rc0.dist-info/METADATA
carrier.dhl_ecom_de-2021.10rc0.dist-info/RECORD
