Metadata-Version: 2.1
Name: carrier.dhl-ecom-de
Version: 2021.10rc0
Summary: DHL eCommerce Germany Web API Schemas Python Data Types library
Home-page: https://github.com/purplship/purplship-carriers/tree/master/carrier.dhl_ecom_de
License: MIT
Author: Dan Kobina
Author-email: danielkobina@gmail.com
Requires-Python: >=3.6,<4.0
Classifier: Intended Audience :: Developers
Classifier: License :: OSI Approved :: MIT License
Classifier: Operating System :: OS Independent
Classifier: Programming Language :: Python :: 3
Classifier: Programming Language :: Python :: 3.10
Classifier: Programming Language :: Python :: 3.6
Classifier: Programming Language :: Python :: 3.7
Classifier: Programming Language :: Python :: 3.8
Classifier: Programming Language :: Python :: 3.9
Requires-Dist: lxml
Requires-Dist: six
Project-URL: Repository, https://github.com/purplship/purplship-carriers
